{"_wandb":{"runtime":11},"test_vis/rug plot and empirical cdf plot of number of inputs per predicted cluster for facet 1":{"size":16402,"path":"media/images/test_vis/rug plot and empirical cdf plot of number of inputs per predicted cluster for facet 1_0_bae9092f65702f37d7ea.png","format":"png","width":640,"height":480,"_type":"image-file","sha256":"bae9092f65702f37d7ea2910b4c3b98e0e7abb358710437d58c1ef4bbd88865e"},"test_vis/input and reconstruction facet 1 (sorted, cluster size from large to small)":{"width":800,"height":200,"_type":"image-file","sha256":"5fd425631c1441fdb25087eb333188649864e29f8f3ba425933d79f915a6c65b","size":9326,"path":"media/images/test_vis/input and reconstruction facet 1 (sorted, cluster size from large to small)_0_5fd425631c1441fdb250.png","format":"png"},"epoch":0,"test_vis/confusion matrix facet 1":{"height":100,"_type":"image-file","sha256":"c064c693e86df028284b9329d1c07c5ed4940c9d393bd5257811bc5f307710f5","size":2750,"path":"media/images/test_vis/confusion matrix facet 1_0_c064c693e86df028284b.png","format":"png","width":100},"test_metric/clusters_present_1":2,"_step":0,"sample_generation/cluster sample generations facet 0 (rows sorted by average confidence)":{"sha256":"ea78a020e1ef9790ef97be6bdb3548059b99541aaaebce02626be4f27bdadc8b","size":12244,"path":"media/images/sample_generation/cluster sample generations facet 0 (rows sorted by average confidence)_0_ea78a020e1ef9790ef97.png","format":"png","width":800,"height":200,"_type":"image-file"},"test_vis/input and reconstruction facet 0 (sorted, cluster size from large to small)":{"height":200,"_type":"image-file","sha256":"93060a1d98e0d315512d7bcb8d74fdc0d1b36b51f08b9f1c6dc77e57b2122dc0","size":9256,"path":"media/images/test_vis/input and reconstruction facet 0 (sorted, cluster size from large to small)_0_93060a1d98e0d315512d.png","format":"png","width":800},"sample_generation/cluster sample generations facet 1 (rows sorted by average confidence)":{"size":12139,"path":"media/images/sample_generation/cluster sample generations facet 1 (rows sorted by average confidence)_0_b1d58c50379bb4c71286.png","format":"png","width":800,"height":200,"_type":"image-file","sha256":"b1d58c50379bb4c71286bac142a23c76415bf32d56a61a7f6620e327198f3124"},"epoch_lr":0.0005,"test_metric/loss":532.1840209960938,"test_vis/confusion matrix facet 0":{"height":100,"_type":"image-file","sha256":"9d45f17f44e927efc1fe83cd12ff303340ab2167194c2f58a5f39792ceb40561","size":2290,"path":"media/images/test_vis/confusion matrix facet 0_0_9d45f17f44e927efc1fe.png","format":"png","width":100},"_runtime":11.164294977,"test_metric/facet_acc_mean":0.5318181818181817,"test_vis/cluster examples facet 0 (rows sorted by average confidence)":{"path":"media/images/test_vis/cluster examples facet 0 (rows sorted by average confidence)_0_7cd48cf5979ce0bf56c3.png","format":"png","width":1000,"height":200,"_type":"image-file","sha256":"7cd48cf5979ce0bf56c3ddf13c9ce4b373c92b1cbb4e3bab081816601e483aac","size":2994},"test_metric/facet_1_acc_max":0.5344988344988345,"_timestamp":1.7616664500877302e+09,"test_vis/rug plot and empirical cdf plot of number of inputs per predicted cluster for facet 0":{"sha256":"1ff111fc72945cbcf7fac80714d3f4542d4a282b4e6ef2cbe6d3b9982cfd546d","size":16199,"path":"media/images/test_vis/rug plot and empirical cdf plot of number of inputs per predicted cluster for facet 0_0_1ff111fc72945cbcf7fa.png","format":"png","width":640,"height":480,"_type":"image-file"},"test_metric/facet_acc_max":0.5344988344988345,"test_metric/clusters_present_0":2,"test_metric/facet_0_acc_max":0.5291375291375291,"test_metric/facet_acc_sum":1.0636363636363635,"test_vis/cluster examples facet 1 (rows sorted by average confidence)":{"height":200,"_type":"image-file","sha256":"41e94b924bb789cb3c2412113974c752681dbb196978f6c3f78f9f328a5a889d","size":3074,"path":"media/images/test_vis/cluster examples facet 1 (rows sorted by average confidence)_0_41e94b924bb789cb3c24.png","format":"png","width":1000}}